clarence.py
clarence-0.2.1.dist-info/METADATA
clarence-0.2.1.dist-info/WHEEL
clarence-0.2.1.dist-info/RECORD
