Metadata-Version: 2.4
Name: clarence
Version: 0.2.1
Summary: A utility for working with pass
Author-email: Hamed Bastan-Hagh <hamed@bastanhagh.com>
Requires-Python: >=3.10
